test_basic_packet/__init__.py
test_basic_packet/api/__ini__.py
test_basic_packet/api/__init__.py
test_basic_packet/api/debug_talk.py
test_basic_packet/api/main.py
test_basic_packet/api/money_settle.py
test_basic_packet/api/setting.py
test_basic_packet/api/base/__init__.py
test_basic_packet/api/base/http_client.py
test_basic_packet/api/base/parser.py
test_basic_packet/api/data/__init__.py
test_basic_packet/api/data/org_category/__init__.py
test_basic_packet/api/db/__init__.py
test_basic_packet/api/db/mysql_db.py
test_basic_packet/api/db/postgre_db.py
test_basic_packet/api/db/redis_db.py
test_basic_packet/api/testcases/__init__.py
test_basic_packet/api/testcases/conftest.py
test_basic_packet/api/testcases/login/__init__.py
test_basic_packet/api/testcases/login/test_login.py
test_basic_packet/api/testcases/org_category/__init__.py
test_basic_packet/api/testcases/org_category/test_org_category.py
test_basic_packet/api/utils/__init__.py
test_basic_packet/api/utils/__int__.py
test_basic_packet/api/utils/data.py
test_basic_packet/api/utils/logger.py
test_basic_packet/api/utils/read_data.py
test_basic_packet/common/__init__.py
test_basic_packet/common/plugin.py
test_basic_packet/config/__init__.py
test_basic_packet/config/config.py
test_basic_packet/ui/__init__.py
test_basic_packet/ui/base_page/BasePage.py
test_basic_packet/ui/base_page/__init__.py
test_basic_packet/ui/buildIn_library/BuildInLibrary.py
test_basic_packet/ui/buildIn_library/__init__.py
test_basic_packet-0.0.2.dist-info/METADATA
test_basic_packet-0.0.2.dist-info/WHEEL
test_basic_packet-0.0.2.dist-info/top_level.txt
test_basic_packet-0.0.2.dist-info/RECORD
