Metadata-Version: 2.1
Name: test-basic-packet
Version: 0.0.2
Summary: python 自动化测试基础包
Author: 自动化测试基础包
Author-email: tianjincn@163.com
